exceptions/__init__.py
exceptions/exceptions.py
sdputils/__init__.py
sdputils/exceptions.py
sdputils/sdputils.py
sdputils/teste.py
sdputils-1.0.4.10.dist-info/METADATA
sdputils-1.0.4.10.dist-info/WHEEL
sdputils-1.0.4.10.dist-info/top_level.txt
sdputils-1.0.4.10.dist-info/RECORD
