Metadata-Version: 2.1
Name: sdputils
Version: 1.0.4.10
Summary: Utils' functions to use inside the Semantix Data Platform for data transformation.
Author: Lucas S. Maximiano
License: UNKNOWN
Platform: UNKNOWN
Requires-Dist: pandas (==1.2.4)
Requires-Dist: sqlalchemy (==1.4.9)
Requires-Dist: pyhive (==0.6.5)
Requires-Dist: unidecode (==1.3.3)
